{
  "color": {
    "c0": {
      "50": {
        "value": "#F9FAFB",
        "type": "color"
      },
      "100": {
        "value": "#F4F5F7",
        "type": "color"
      },
      "200": {
        "value": "#E5E7EB",
        "type": "color"
      },
      "300": {
        "value": "#D2D6DC",
        "type": "color"
      },
      "400": {
        "value": "#9FA6B2",
        "type": "color"
      },
      "500": {
        "value": "#6B7280",
        "type": "color"
      },
      "600": {
        "value": "#4B5563",
        "type": "color"
      },
      "700": {
        "value": "#374151",
        "type": "color"
      },
      "800": {
        "value": "#252F3F",
        "type": "color"
      },
      "900": {
        "value": "#161E2E",
        "type": "color"
      }
    },
    "c1": {
      "50": {
        "value": "#F2F4F9",
        "type": "color"
      },
      "100": {
        "value": "#E6E9F3",
        "type": "color"
      },
      "200": {
        "value": "#BFC9E1",
        "type": "color"
      },
      "300": {
        "value": "#99A8CF",
        "type": "color"
      },
      "400": {
        "value": "#4D67AC",
        "type": "color"
      },
      "500": {
        "value": "#002688",
        "type": "color"
      },
      "600": {
        "value": "#00227A",
        "type": "color"
      },
      "700": {
        "value": "#001752",
        "type": "color"
      },
      "800": {
        "value": "#00113D",
        "type": "color"
      },
      "900": {
        "value": "#000B29",
        "type": "color"
      }
    },
    "c2": {
      "50": {
        "value": "#F2F9F9",
        "type": "color"
      },
      "100": {
        "value": "#E6F2F4",
        "type": "color"
      },
      "200": {
        "value": "#C0DFE3",
        "type": "color"
      },
      "300": {
        "value": "#9ACCD3",
        "type": "color"
      },
      "400": {
        "value": "#4EA6B1",
        "type": "color"
      },
      "500": {
        "value": "#028090",
        "type": "color"
      },
      "600": {
        "value": "#027382",
        "type": "color"
      },
      "700": {
        "value": "#014D56",
        "type": "color"
      },
      "800": {
        "value": "#013A41",
        "type": "color"
      },
      "900": {
        "value": "#01262B",
        "type": "color"
      }
    },
    "cBlack": {
      "value": "#161616",
      "type": "color"
    },
    "cWhite": {
      "value": "#ffffff",
      "type": "color"
    },
    "cError": {
      "100": {
        "value": "#F5CCDD",
        "type": "color"
      },
      "500": {
        "value": "#D70B3B",
        "type": "color"
      }
    },
    "cSuccess": {
      "100": {
        "value": "#D4EFDF",
        "type": "color"
      },
      "500": {
        "value": "#27AE60",
        "type": "color"
      }
    },
    "cWarning": {
      "100": {
        "value": "#FFE3BB",
        "type": "color"
      },
      "500": {
        "value": "#FF9900",
        "type": "color"
      }
    }
  }
}